[{"id":1,"title":"hossam","status":"in-progress"},{"id":3,"title":"alaa","status":"done"},{"id":4,"title":"mahmoud","status":"false"},{"id":5,"title":"hossam","status":"done"},{"id":6,"title":"als","status":"to-do"},{"id":7,"title":"alsi","status":"to-do"},{"id":8,"title":"alsiaa","status":"to-do"},{"id":9,"title":"as3addd","status":"to-do"},{"id":10,"title":"assssde","status":"todo"},{"id":11,"title":"assssde","status":"to-do"},{"id":12,"title":"assssdess","status":"asd"},{"id":13,"title":"assssdess","status":"aasdsd"},{"id":14,"title":"assssdess","status":"aasdsd"},{"id":15,"title":"ahmed","status":"aasdsd"},{"id":16,"title":"alaa","status":"to-do"},{"id":17,"title":"ali","status":"done"},{"id":18,"title":"ali amed","status":"done"},{"id":19,"title":"amed","status":"to-do"},{"id":20,"title":"amedlsl"},{"id":21,"title":"amedlsl"},{"id":23,"title":"amedlsl","status":"to-do"},{"id":24,"title":"amedlsl","status":"to-do"},{"id":25,"title":"amedlsl","status":"done"},{"id":26,"title":"ali","status":"to-do"},{"id":27,"title":"ali","status":"in-progress"},{"id":28,"title":"ENG.Mahmoud","status":"to-do"}]